spacy_token_parser/__init__.py
spacy_token_parser/dmo/__init__.py
spacy_token_parser/dmo/token_parser_coordinates.py
spacy_token_parser/dmo/token_parser_normalize.py
spacy_token_parser/dmo/token_parser_postprocess.py
spacy_token_parser/dmo/token_parser_punctuation.py
spacy_token_parser/dmo/token_parser_resultset.py
spacy_token_parser/dmo/token_parser_spacy.py
spacy_token_parser/dmo/token_parser_squots.py
spacy_token_parser/dmo/token_parser_wordnet.py
spacy_token_parser/dto/__init__.py
spacy_token_parser/dto/typedefs.py
spacy_token_parser/svc/__init__.py
spacy_token_parser/svc/create_graph_structure.py
spacy_token_parser/svc/generate_displacy_output.py
spacy_token_parser/svc/parse_input_tokens.py
spacy_token_parser-0.1.16.dist-info/METADATA
spacy_token_parser-0.1.16.dist-info/WHEEL
spacy_token_parser-0.1.16.dist-info/RECORD
