Metadata-Version: 2.1
Name: spacy-token-parser
Version: 0.1.16
Summary: Use spaCy to Parse Input Tokens
Home-page: https://github.com/craigtrim/spacy-token-parser
License: None
Keywords: nlp,nlu,ai,parser,spacy
Author: Craig Trim
Author-email: craigtrim@gmail.com
Maintainer: Craig Trim
Maintainer-email: craigtrim@gmail.com
Requires-Python: >=3.8.5,<4.0.0
Classifier: Development Status :: 4 - Beta
Classifier: License :: Other/Proprietary License
Classifier: Programming Language :: Python :: 3
Classifier: Programming Language :: Python :: 3.9
Classifier: Programming Language :: Python :: 3.10
Classifier: Programming Language :: Python :: 3.11
Classifier: Topic :: Scientific/Engineering :: Artificial Intelligence
Classifier: Topic :: Software Development :: Libraries :: Python Modules
Requires-Dist: baseblock
Requires-Dist: nltk (==3.8.1)
Requires-Dist: spacy (==3.5.0)
Requires-Dist: wordnet-lookup
Project-URL: Bug Tracker, https://github.com/craigtrim/spacy-token-parser/issues
Project-URL: Repository, https://github.com/craigtrim/spacy-token-parser
